<?xml version='1.0' encoding='ISO-8859-1'?>
<GateDocument version="3">
<!-- The document's features-->

<GateDocumentFeatures>
<Feature>
  <Name className="java.lang.String">gate.SourceURL</Name>
  <Value className="java.lang.String">file:/C:/Documents%20and%20Settings/Administrator/Desktop/horacio-sandra/ferroviarios/tren-270688e.txt</Value>
</Feature>
<Feature>
  <Name className="java.lang.String">MimeType</Name>
  <Value className="java.lang.String">text/plain</Value>
</Feature>
<Feature>
  <Name className="java.lang.String">docNewLineType</Name>
  <Value className="java.lang.String"></Value>
</Feature>
</GateDocumentFeatures>
<!-- The document content area with serialized nodes -->

<TextWithNodes><Node id="0"/>June 27, 1988<Node id="13"/> ? Gare de Lyon train accident, <Node id="45"/>Gare de Lyon, Paris, France<Node id="72"/>: After <Node id="80"/>brake failure<Node id="93"/>, <Node id="95"/>runaway train<Node id="108"/> hits<Node id="113"/> stationary <Node id="125"/>rush-hour train<Node id="140"/> in station, <Node id="153"/>56<Node id="155"/> people killed, over <Node id="176"/>50<Node id="178"/> injured.<Node id="187"/></TextWithNodes>
<!-- The default annotation set -->

<AnnotationSet>
</AnnotationSet>

<!-- Named annotation set -->

<AnnotationSet Name="Gold">
<Annotation Id="84" Type="Mention" StartNode="0" EndNode="13">
<Feature>
  <Name className="java.lang.String">type</Name>
  <Value className="java.lang.String">DateOfAccident</Value>
</Feature>
</Annotation>
<Annotation Id="85" Type="Mention" StartNode="45" EndNode="72">
<Feature>
  <Name className="java.lang.String">type</Name>
  <Value className="java.lang.String">Place</Value>
</Feature>
</Annotation>
<Annotation Id="86" Type="Mention" StartNode="80" EndNode="93">
<Feature>
  <Name className="java.lang.String">type</Name>
  <Value className="java.lang.String">Cause</Value>
</Feature>
</Annotation>
<Annotation Id="87" Type="Mention" StartNode="108" EndNode="113">
<Feature>
  <Name className="java.lang.String">type</Name>
  <Value className="java.lang.String">TypeOfAccident</Value>
</Feature>
</Annotation>
<Annotation Id="88" Type="Mention" StartNode="153" EndNode="155">
<Feature>
  <Name className="java.lang.String">type</Name>
  <Value className="java.lang.String">NumberOfVictims</Value>
</Feature>
</Annotation>
<Annotation Id="89" Type="Mention" StartNode="176" EndNode="178">
<Feature>
  <Name className="java.lang.String">type</Name>
  <Value className="java.lang.String">Survivors</Value>
</Feature>
</Annotation>
<Annotation Id="90" Type="Mention" StartNode="95" EndNode="108">
<Feature>
  <Name className="java.lang.String">type</Name>
  <Value className="java.lang.String">TypeOfTrain</Value>
</Feature>
</Annotation>
<Annotation Id="91" Type="Mention" StartNode="125" EndNode="140">
<Feature>
  <Name className="java.lang.String">type</Name>
  <Value className="java.lang.String">TypeOfTrain</Value>
</Feature>
</Annotation>
</AnnotationSet>

<!-- Named annotation set -->

<AnnotationSet Name="Original markups">
<Annotation Id="0" Type="paragraph" StartNode="0" EndNode="187">
</Annotation>
</AnnotationSet>

<!-- Named annotation set -->

<AnnotationSet Name="sms">
<Annotation Id="1" Type="DateOfAccident" StartNode="0" EndNode="13">
<Feature>
  <Name className="java.lang.String">name</Name>
  <Value className="java.lang.String">27/06/1988</Value>
</Feature>
</Annotation>
<Annotation Id="4" Type="Place" StartNode="45" EndNode="72">
</Annotation>
<Annotation Id="6" Type="Cause" StartNode="80" EndNode="93">
</Annotation>
<Annotation Id="7" Type="TypeOfAccident" StartNode="108" EndNode="113">
</Annotation>
<Annotation Id="8" Type="NumberOfVictims" StartNode="153" EndNode="155">
</Annotation>
<Annotation Id="9" Type="Survivors" StartNode="176" EndNode="178">
</Annotation>
<Annotation Id="10" Type="TypeOfTrain" StartNode="95" EndNode="108">
<Feature>
  <Name className="java.lang.String">name</Name>
  <Value className="java.lang.String">1</Value>
</Feature>
</Annotation>
<Annotation Id="11" Type="TypeOfTrain" StartNode="125" EndNode="140">
<Feature>
  <Name className="java.lang.String">name</Name>
  <Value className="java.lang.String">2</Value>
</Feature>
</Annotation>
</AnnotationSet>

</GateDocument>
