<?xml version='1.0' encoding='ISO-8859-1'?>
<GateDocument version="3">
<!-- The document's features-->

<GateDocumentFeatures>
<Feature>
  <Name className="java.lang.String">gate.SourceURL</Name>
  <Value className="java.lang.String">file:/C:/Documents%20and%20Settings/Administrator/Desktop/horacio-sandra/terremotos/terremoto-100597.txt</Value>
</Feature>
<Feature>
  <Name className="java.lang.String">MimeType</Name>
  <Value className="java.lang.String">text/plain</Value>
</Feature>
<Feature>
  <Name className="java.lang.String">docNewLineType</Name>
  <Value className="java.lang.String">CRLF</Value>
</Feature>
</GateDocumentFeatures>
<!-- The document content area with serialized nodes -->

<TextWithNodes><Node id="0"/>10 mayo 1997&#xd;<Node id="13"/>
<Node id="14"/>Este de Irán<Node id="26"/>, especialmente la provincia de <Node id="58"/>Jorasán<Node id="65"/>: al menos <Node id="76"/>1.560<Node id="81"/> muertos en un seísmo de magnitud <Node id="115"/>7,1<Node id="118"/> grados Richter.<Node id="134"/></TextWithNodes>
<!-- The default annotation set -->

<AnnotationSet>
</AnnotationSet>

<!-- Named annotation set -->

<AnnotationSet Name="Gold">
<Annotation Id="64" Type="Mention" StartNode="14" EndNode="26">
<Feature>
  <Name className="java.lang.String">type</Name>
  <Value className="java.lang.String">Region</Value>
</Feature>
</Annotation>
<Annotation Id="65" Type="Mention" StartNode="58" EndNode="65">
<Feature>
  <Name className="java.lang.String">type</Name>
  <Value className="java.lang.String">Province</Value>
</Feature>
</Annotation>
<Annotation Id="66" Type="Mention" StartNode="76" EndNode="81">
<Feature>
  <Name className="java.lang.String">type</Name>
  <Value className="java.lang.String">Fatalities</Value>
</Feature>
</Annotation>
<Annotation Id="67" Type="Mention" StartNode="115" EndNode="118">
<Feature>
  <Name className="java.lang.String">type</Name>
  <Value className="java.lang.String">Magnitude</Value>
</Feature>
</Annotation>
<Annotation Id="63" Type="Mention" StartNode="0" EndNode="13">
<Feature>
  <Name className="java.lang.String">type</Name>
  <Value className="java.lang.String">DateOfEarthquake</Value>
</Feature>
</Annotation>
</AnnotationSet>

<!-- Named annotation set -->

<AnnotationSet Name="Original markups">
<Annotation Id="0" Type="paragraph" StartNode="0" EndNode="134">
</Annotation>
</AnnotationSet>

<!-- Named annotation set -->

<AnnotationSet Name="sms">
<Annotation Id="1" Type="DateOfEarthquake" StartNode="0" EndNode="13">
<Feature>
  <Name className="java.lang.String">name</Name>
  <Value className="java.lang.String">10/05/1997</Value>
</Feature>
</Annotation>
<Annotation Id="2" Type="Region" StartNode="14" EndNode="26">
<Feature>
  <Name className="java.lang.String">name</Name>
  <Value className="java.lang.String"></Value>
</Feature>
</Annotation>
<Annotation Id="3" Type="Province" StartNode="58" EndNode="65">
</Annotation>
<Annotation Id="4" Type="Fatalities" StartNode="76" EndNode="81">
</Annotation>
<Annotation Id="5" Type="Magnitude" StartNode="115" EndNode="118">
</Annotation>
</AnnotationSet>

</GateDocument>
